{
  "game_id": "fox-in-the-forest",
  "title": "Fox in the Forest",
  "sections": {
    "setup": {
      "walkthrough": [
        {
          "step": 1,
          "title": "Gather the Components",
          "text": "Let's get Fox in the Forest set up. You will need the 33 cards in three suits: Bells, Keys, and Moons, each numbered one through eleven. You also need the scoring tokens and the score track. Set the score track on the table between both players.",
          "image": null,
          "image_caption": null
        },
        {
          "step": 2,
          "title": "Shuffle and Deal",
          "text": "Give all 33 cards a good shuffle. Deal 13 cards face down to each player. That leaves seven cards remaining. One of those seven will become the trump card, and the other six form the draw deck.",
          "image": null,
          "image_caption": null
        },
        {
          "step": 3,
          "title": "Reveal the Trump Card",
          "text": "Take the top card of the remaining pile and place it face up on the table. This card determines the trump suit for the round. Whatever suit this card shows, that suit beats all other suits when played. Place the remaining six cards face down as the draw deck.",
          "image": null,
          "image_caption": null
        },
        {
          "step": 4,
          "title": "Note the Card Abilities",
          "text": "Before you start, remember that odd-numbered cards have special abilities. The one, three, five, seven, nine, and eleven each do something unique when played. We will cover these in the rules section. Keep your player aid card handy for quick reference.",
          "image": null,
          "image_caption": null
        },
        {
          "step": 5,
          "title": "Place Scoring Tokens",
          "text": "Each player places their scoring token on position zero of the score track. You will move these tokens as you score points across multiple rounds. The game continues until someone reaches 21 points.",
          "image": null,
          "image_caption": null
        },
        {
          "step": 6,
          "title": "Determine Who Leads",
          "text": "The non-dealer leads the first trick. Pick up your 13 cards and look at your hand. You will play 13 tricks this round. Ready to learn the rules? Let's go.",
          "image": null,
          "image_caption": null
        }
      ],
      "summary": [
        {
          "step": 1,
          "title": "Gather the Components",
          "bullets": [
            "33 cards in 3 suits (Bells, Keys, Moons), numbered 1-11",
            "Scoring tokens + score track between players"
          ]
        },
        {
          "step": 2,
          "title": "Shuffle and Deal",
          "bullets": [
            "Shuffle all 33 cards",
            "Deal 13 cards face down to each player",
            "7 cards remain for trump + draw deck"
          ]
        },
        {
          "step": 3,
          "title": "Reveal the Trump Card",
          "bullets": [
            "Flip top card face up = trump suit for the round",
            "Trump suit beats non-trump when played",
            "Remaining 6 cards form the draw deck"
          ]
        },
        {
          "step": 4,
          "title": "Note the Card Abilities",
          "bullets": [
            "Odd-numbered cards (1, 3, 5, 7, 9, 11) have special abilities",
            "Keep player aid card handy for reference"
          ]
        },
        {
          "step": 5,
          "title": "Place Scoring Tokens",
          "bullets": [
            "Both scoring tokens start at position 0",
            "Game plays over multiple rounds to 21 points"
          ]
        },
        {
          "step": 6,
          "title": "Determine Who Leads",
          "bullets": [
            "Non-dealer leads the first trick",
            "13 tricks played per round"
          ]
        }
      ]
    },
    "rules": {
      "walkthrough": [
        {
          "step": 1,
          "title": "Game Overview",
          "text": "Fox in the Forest is a two-player trick-taking card game with a unique twist. Winning too many tricks is greedy and scores you zero points. You need to find the sweet spot, winning just enough tricks to score well without getting punished for being too dominant.",
          "image": null,
          "image_caption": null
        },
        {
          "step": 2,
          "title": "Playing a Trick",
          "text": "The leader plays any card from their hand. The other player must follow suit if they can. If you cannot follow suit, you may play any card from your hand, including a trump card. The highest card of the led suit wins the trick, unless a trump card was played, in which case the highest trump wins.",
          "image": null,
          "image_caption": null
        },
        {
          "step": 3,
          "title": "After a Trick",
          "text": "The winner of the trick collects both cards and places them face down in their trick pile. The winner then leads the next trick. Continue until all 13 tricks have been played.",
          "image": null,
          "image_caption": null
        },
        {
          "step": 4,
          "title": "The Trump Suit",
          "text": "The face-up card next to the draw deck determines the trump suit for the round. Trump cards beat any non-trump card regardless of number. If both players play trump, the higher trump wins. The trump suit adds a layer of strategy to every trick.",
          "image": null,
          "image_caption": null
        },
        {
          "step": 5,
          "title": "Card Abilities: Swan and Fox",
          "text": "Let's go through the special abilities on odd-numbered cards. The one is the Swan. If you play it and lose the trick, you lead the next trick instead of the winner. The three is the Fox. When you play it, you may swap the face-up trump card with a card from your hand.",
          "image": null,
          "image_caption": null
        },
        {
          "step": 6,
          "title": "Card Abilities: Woodcutter and Treasure",
          "text": "The five is the Woodcutter. When you play it, draw one card from the draw deck, then discard one card face down. This lets you improve your hand. The seven is the Treasure. Whoever wins the trick containing the seven scores one bonus point.",
          "image": null,
          "image_caption": null
        },
        {
          "step": 7,
          "title": "Card Abilities: Witch and Monarch",
          "text": "The nine is the Witch. If you lead with the Witch, it counts as trump regardless of its actual suit. This is a powerful surprise play. The eleven is the Monarch. You must play it if it is your only card of the led suit. This is a restriction, not a benefit.",
          "image": null,
          "image_caption": null
        },
        {
          "step": 8,
          "title": "The Scoring Table",
          "text": "Here is where Fox in the Forest gets interesting. Your score depends on how many tricks you win. Zero to three tricks is Humble and scores six points. Four tricks scores one point. Five tricks scores two. Six tricks scores three. Seven to nine tricks is Victorious and scores six points. But ten to thirteen tricks is Greedy and scores zero points.",
          "image": null,
          "image_caption": null
        },
        {
          "step": 9,
          "title": "The Greedy Trap",
          "text": "Let's emphasize the greedy rule because it changes everything. If you win ten or more tricks out of thirteen, you score zero for the round. This means your opponent can deliberately feed you tricks to push you into greed territory. It is not just about winning tricks. It is about winning the right number of tricks.",
          "image": null,
          "image_caption": null
        },
        {
          "step": 10,
          "title": "Winning the Game",
          "text": "At the end of each round, count your tricks and score accordingly. Move your scoring token on the track. Shuffle all cards, redeal, and play another round. The first player to reach 21 points wins the game. Most games take three to four rounds.",
          "image": null,
          "image_caption": null
        }
      ],
      "summary": [
        {
          "step": 1,
          "title": "Game Overview",
          "bullets": [
            "2-player trick-taking game",
            "Winning too many tricks = greedy = 0 points",
            "Find the scoring sweet spot"
          ]
        },
        {
          "step": 2,
          "title": "Playing a Trick",
          "bullets": [
            "Leader plays any card, follower must follow suit if able",
            "Can't follow suit = play any card (including trump)",
            "Highest led suit wins, unless trump played (highest trump wins)"
          ]
        },
        {
          "step": 3,
          "title": "After a Trick",
          "bullets": [
            "Winner collects both cards face down",
            "Winner leads the next trick",
            "Play all 13 tricks per round"
          ]
        },
        {
          "step": 4,
          "title": "The Trump Suit",
          "bullets": [
            "Face-up card determines trump suit",
            "Trump beats any non-trump card",
            "If both play trump, higher trump wins"
          ]
        },
        {
          "step": 5,
          "title": "Card Abilities: Swan and Fox",
          "bullets": [
            "1 (Swan): lose the trick → you still lead next",
            "3 (Fox): swap trump card with a card from your hand"
          ]
        },
        {
          "step": 6,
          "title": "Card Abilities: Woodcutter and Treasure",
          "bullets": [
            "5 (Woodcutter): draw 1 from deck, discard 1 face down",
            "7 (Treasure): winner of this trick scores +1 bonus point"
          ]
        },
        {
          "step": 7,
          "title": "Card Abilities: Witch and Monarch",
          "bullets": [
            "9 (Witch): counts as trump when led",
            "11 (Monarch): must play it if it's your only card of led suit"
          ]
        },
        {
          "step": 8,
          "title": "The Scoring Table",
          "bullets": [
            "0-3 tricks (Humble) = 6 pts",
            "4 tricks = 1 pt, 5 = 2 pts, 6 = 3 pts",
            "7-9 tricks (Victorious) = 6 pts",
            "10-13 tricks (Greedy) = 0 pts!"
          ]
        },
        {
          "step": 9,
          "title": "The Greedy Trap",
          "bullets": [
            "10+ tricks = 0 points for the round",
            "Opponent can feed you tricks to push you into greed",
            "Winning tricks ≠ winning the game"
          ]
        },
        {
          "step": 10,
          "title": "Winning the Game",
          "bullets": [
            "Score at end of each round, move token on track",
            "Reshuffle, redeal, play another round",
            "First to 21 points wins (usually 3-4 rounds)"
          ]
        }
      ]
    },
    "practice_tutorial": {
      "walkthrough": [
        {
          "step": 1,
          "title": "Welcome to the Forest",
          "text": "Welcome to your first game of Fox in the Forest! In this tutorial, we will walk through several tricks between two example players, Alice and Bob. Alice is the non-dealer and will lead the first trick. The trump suit is Bells.",
          "image": null,
          "image_caption": null
        },
        {
          "step": 2,
          "title": "Trick One: A Simple Lead",
          "text": "Alice leads with the eight of Moons. Bob has Moons in his hand, so he must follow suit. He plays the ten of Moons. Ten beats eight, so Bob wins the trick. Bob collects both cards and will lead the next trick. Simple so far.",
          "image": null,
          "image_caption": null
        },
        {
          "step": 3,
          "title": "Trick Two: Playing Trump",
          "text": "Bob leads with the six of Keys. Alice has no Keys in her hand, so she is free to play any card. She plays the two of Bells, which is the trump suit. Even though two is a low number, trump beats non-trump. Alice wins the trick.",
          "image": null,
          "image_caption": null
        },
        {
          "step": 4,
          "title": "Trick Three: The Swan",
          "text": "Alice leads with the one of Moons, the Swan. Bob plays the four of Moons. Bob wins because four beats one. But the Swan's ability triggers. Even though Alice lost the trick, she gets to lead the next trick instead of Bob. The Swan gives you control of the lead.",
          "image": null,
          "image_caption": null
        },
        {
          "step": 5,
          "title": "Trick Four: The Fox",
          "text": "Alice leads the three of Bells, the Fox. The Fox's ability lets Alice swap the face-up trump card with a card from her hand. She swaps a weak card for the trump card, improving her hand. Then Bob follows suit and the trick resolves normally.",
          "image": null,
          "image_caption": null
        },
        {
          "step": 6,
          "title": "Trick Five: The Witch Surprise",
          "text": "Alice leads the nine of Keys, the Witch. Even though it is a Keys card, the Witch counts as trump when led. Bob must follow with Keys if he has them. But the Witch is treated as the highest possible trump for winning purposes. Alice wins the trick.",
          "image": null,
          "image_caption": null
        },
        {
          "step": 7,
          "title": "Counting Tricks at Midgame",
          "text": "Let's pause and count. After several tricks, Alice has won five and Bob has won four. Both are in scoring range. But Alice needs to be careful. If she wins five more, she will hit ten total, which is greedy territory and scores zero.",
          "image": null,
          "image_caption": null
        },
        {
          "step": 8,
          "title": "The Greedy Trap in Action",
          "text": "Bob realizes Alice is winning a lot of tricks. He starts deliberately losing tricks by playing low cards when he leads. Alice wins three more tricks, pushing her to eight. She is still safe in the Victorious range. But two more wins would be dangerous.",
          "image": null,
          "image_caption": null
        },
        {
          "step": 9,
          "title": "Alice Adjusts Her Strategy",
          "text": "Alice recognizes the danger. She starts playing low cards and avoiding trump to stop winning tricks. She intentionally loses the next two tricks. Her final count is eight tricks, landing in the Victorious zone for six points. Smart play.",
          "image": null,
          "image_caption": null
        },
        {
          "step": 10,
          "title": "Common Mistake: Being Too Greedy",
          "text": "In a different game, Alice does not watch her trick count. She plays aggressively, winning trick after trick with powerful trump cards. She ends the round with eleven tricks. That is Greedy. She scores zero points while Bob scores six for the Humble category with only two tricks won.",
          "image": null,
          "image_caption": null
        },
        {
          "step": 11,
          "title": "Lesson: Count Your Tricks",
          "text": "The lesson here is simple. Always count how many tricks you and your opponent have won. The scoring table is the whole game. Aim for seven to nine tricks if you are ahead, or zero to three if you are behind. The middle ground of four to six tricks scores poorly.",
          "image": null,
          "image_caption": null
        },
        {
          "step": 12,
          "title": "Common Mistake: Ignoring Abilities",
          "text": "Bob has the Woodcutter in his hand for several tricks but never plays it. He forgets that the five lets him draw a card and discard one, which could have improved his hand dramatically. Meanwhile, Alice uses every ability to her advantage.",
          "image": null,
          "image_caption": null
        },
        {
          "step": 13,
          "title": "Lesson: Use Your Special Cards",
          "text": "Do not forget about card abilities. The Fox, Woodcutter, Swan, and Witch are powerful tools that can swing the game. Plan when to play them for maximum impact rather than letting them sit unused in your hand.",
          "image": null,
          "image_caption": null
        },
        {
          "step": 14,
          "title": "End of Round Scoring",
          "text": "All 13 tricks are done. Alice won eight tricks for six points. Bob won five tricks for two points. Move the scoring tokens on the track. Shuffle all cards, deal a new hand of 13 each, flip a new trump card, and start another round.",
          "image": null,
          "image_caption": null
        },
        {
          "step": 15,
          "title": "Congratulations",
          "text": "Congratulations, you have played through your first round of Fox in the Forest! You have seen how tricks work, how trump changes the game, and how the greedy scoring keeps both players honest. Remember to count your tricks, use your abilities, and watch for the greed trap.",
          "image": null,
          "image_caption": null
        },
        {
          "step": 16,
          "title": "Before You Play",
          "text": "Before you start a full game, here are three things that can help.\n\nFirst, check out General Tips for strategy on managing your trick count.\n\nSecond, reference the Appendix for a quick guide to all card abilities.\n\nAnd most importantly, ask your personal GM Guide for help anytime. Just tap the Q&A tab and ask any question during your game. Have fun!",
          "cta": true
        }
      ],
      "summary": [
        {
          "step": 1,
          "title": "Welcome to the Forest",
          "bullets": [
            "Tutorial with 2 example players: Alice and Bob",
            "Trump suit is Bells for this example",
            "Alice leads the first trick as non-dealer"
          ]
        },
        {
          "step": 2,
          "title": "Trick One: A Simple Lead",
          "bullets": [
            "Alice leads 8 of Moons, Bob follows with 10 of Moons",
            "Higher card of led suit wins",
            "Bob wins and leads next"
          ]
        },
        {
          "step": 3,
          "title": "Trick Two: Playing Trump",
          "bullets": [
            "Bob leads 6 of Keys, Alice has no Keys",
            "Alice plays 2 of Bells (trump) — trump beats non-trump",
            "Even low trump beats high non-trump"
          ]
        },
        {
          "step": 4,
          "title": "Trick Three: The Swan",
          "bullets": [
            "Alice leads 1 (Swan), loses the trick to Bob",
            "Swan ability: Alice leads next trick despite losing",
            "Swan gives control of the lead"
          ]
        },
        {
          "step": 5,
          "title": "Trick Four: The Fox",
          "bullets": [
            "Alice leads 3 (Fox) of Bells",
            "Fox ability: swap trump card with a hand card",
            "Improves Alice's hand"
          ]
        },
        {
          "step": 6,
          "title": "Trick Five: The Witch Surprise",
          "bullets": [
            "Alice leads 9 (Witch) of Keys",
            "Witch counts as trump when led",
            "Powerful surprise play"
          ]
        },
        {
          "step": 7,
          "title": "Counting Tricks at Midgame",
          "bullets": [
            "Alice: 5 tricks, Bob: 4 tricks",
            "Both in scoring range, but Alice must be careful",
            "5 more wins would push Alice to greedy (0 points)"
          ]
        },
        {
          "step": 8,
          "title": "The Greedy Trap in Action",
          "bullets": [
            "Bob deliberately loses tricks to push Alice toward 10+",
            "Alice reaches 8 tricks — still Victorious",
            "Two more wins would be dangerous"
          ]
        },
        {
          "step": 9,
          "title": "Alice Adjusts Her Strategy",
          "bullets": [
            "Alice plays low cards and avoids trump",
            "Intentionally loses 2 tricks to stay at 8",
            "8 tricks = Victorious = 6 points"
          ]
        },
        {
          "step": 10,
          "title": "Common Mistake: Being Too Greedy",
          "bullets": [
            "Alice plays aggressively, wins 11 tricks",
            "11 tricks = Greedy = 0 points",
            "Bob scores 6 for Humble with only 2 tricks"
          ]
        },
        {
          "step": 11,
          "title": "Lesson: Count Your Tricks",
          "bullets": [
            "Always track trick counts for both players",
            "Aim for 7-9 (Victorious) or 0-3 (Humble)",
            "Middle ground (4-6) scores poorly"
          ]
        },
        {
          "step": 12,
          "title": "Common Mistake: Ignoring Abilities",
          "bullets": [
            "Bob holds the Woodcutter but never plays it",
            "Missed opportunity to draw a card and improve hand",
            "Alice uses every ability to her advantage"
          ]
        },
        {
          "step": 13,
          "title": "Lesson: Use Your Special Cards",
          "bullets": [
            "Fox, Woodcutter, Swan, Witch are powerful tools",
            "Plan when to play them for maximum impact",
            "Don't let abilities sit unused in your hand"
          ]
        },
        {
          "step": 14,
          "title": "End of Round Scoring",
          "bullets": [
            "Alice: 8 tricks = 6 pts, Bob: 5 tricks = 2 pts",
            "Move tokens on score track",
            "Reshuffle, deal, new trump, start next round"
          ]
        },
        {
          "step": 15,
          "title": "Congratulations",
          "bullets": [
            "You've played through a full round",
            "Seen tricks, trump, abilities, and the greed trap",
            "Count tricks, use abilities, watch for greed"
          ]
        },
        {
          "step": 16,
          "title": "Before You Play",
          "bullets": [
            "Check out General Tips for trick management strategy",
            "Reference the Appendix for all card abilities",
            "Ask your personal GM Guide via Q&A tab anytime"
          ],
          "cta": true
        }
      ]
    },
    "general_tips": {
      "walkthrough": [
        {
          "step": 1,
          "title": "Common Mistakes to Avoid",
          "text": "Here are the biggest mistakes new Fox in the Forest players make. First, winning as many tricks as possible without watching the count. Second, ignoring card abilities and playing only by the numbers. Third, not tracking your opponent's trick count, which means you cannot push them toward greed. Keep these in mind from your very first round.",
          "image": null,
          "image_caption": null
        },
        {
          "step": 2,
          "title": "Know Your Target Range",
          "text": "Before the first trick, decide your target range based on your hand strength. If you have strong cards and trump, aim for seven to nine tricks, which is the Victorious zone and scores six points. If your hand is weak, pivot to the Humble strategy, aiming for zero to three tricks, which also scores six points. The worst spot is the middle. Four to six tricks scores only one to three points.",
          "image": null,
          "image_caption": null
        },
        {
          "step": 3,
          "title": "Control the Lead",
          "text": "Leading a trick gives you a significant advantage because you choose the suit. The Swan is incredibly powerful because it lets you regain the lead even when you lose a trick. If you have the Swan, play it strategically to take back control at a key moment rather than wasting it early.",
          "image": null,
          "image_caption": null
        },
        {
          "step": 4,
          "title": "Trump Management",
          "text": "Trump cards are your most powerful weapons, but using them all early leaves you vulnerable later. Save at least one trump for the end of the round when you need to win or lose a specific trick. The Fox ability to swap the trump card can also improve your trump holdings if used wisely.",
          "image": null,
          "image_caption": null
        },
        {
          "step": 5,
          "title": "Force Your Opponent into Greed",
          "text": "If your opponent is winning lots of tricks, you can deliberately feed them more by playing low cards and letting them win. Push them above nine tricks and they score zero. This is a legitimate and effective strategy, especially when your hand is weak. Going Humble for six points while forcing them Greedy for zero is a massive swing.",
          "image": null,
          "image_caption": null
        },
        {
          "step": 6,
          "title": "Use the Woodcutter",
          "text": "The Woodcutter lets you draw from the deck and discard a card. This is one of the most flexible abilities in the game. Use it to dig for trump cards, dump a card you do not want, or adjust your hand to match your target trick range. Do not sleep on this ability.",
          "image": null,
          "image_caption": null
        },
        {
          "step": 7,
          "title": "Track Everything",
          "text": "Good Fox in the Forest players track three things constantly: how many tricks each player has won, which high cards have been played, and which suits their opponent might be short on. This information tells you when to push for more tricks, when to stop winning, and when your opponent might be forced to play trump.",
          "image": null,
          "image_caption": null
        },
        {
          "step": 8,
          "title": "Adapt Mid-Round",
          "text": "Your initial plan might not survive contact with the cards. If you aimed for Victorious but your opponent is playing perfectly to force you into Greed, pivot to a different approach. Flexibility is key. The best players adjust their target range multiple times during a single round based on how tricks are falling.",
          "image": null,
          "image_caption": null
        }
      ],
      "summary": [
        {
          "step": 1,
          "title": "Common Mistakes to Avoid",
          "bullets": [
            "Don't win tricks blindly — watch the count",
            "Don't ignore card abilities — they swing games",
            "Track opponent's trick count to exploit the greed rule"
          ]
        },
        {
          "step": 2,
          "title": "Know Your Target Range",
          "bullets": [
            "Strong hand: aim for 7-9 (Victorious, 6 pts)",
            "Weak hand: aim for 0-3 (Humble, 6 pts)",
            "4-6 tricks is the worst scoring zone (1-3 pts)"
          ]
        },
        {
          "step": 3,
          "title": "Control the Lead",
          "bullets": [
            "Leading lets you choose the suit",
            "Swan (1) reclaims the lead even after losing",
            "Save the Swan for a key moment"
          ]
        },
        {
          "step": 4,
          "title": "Trump Management",
          "bullets": [
            "Save at least 1 trump for late-round control",
            "Fox (3) can swap the trump card to improve your hand",
            "Using all trumps early leaves you vulnerable"
          ]
        },
        {
          "step": 5,
          "title": "Force Your Opponent into Greed",
          "bullets": [
            "Deliberately feed tricks to push opponent past 9",
            "Humble (6 pts) + forcing Greedy (0 pts) = massive swing",
            "Effective when your hand is weak"
          ]
        },
        {
          "step": 6,
          "title": "Use the Woodcutter",
          "bullets": [
            "5 (Woodcutter): draw 1 + discard 1 = flexible hand adjustment",
            "Dig for trump, dump weak cards, adjust to target range",
            "One of the most impactful abilities"
          ]
        },
        {
          "step": 7,
          "title": "Track Everything",
          "bullets": [
            "Count tricks won by each player",
            "Note which high cards have been played",
            "Watch for opponent's short suits"
          ]
        },
        {
          "step": 8,
          "title": "Adapt Mid-Round",
          "bullets": [
            "Initial plan may need to change based on card flow",
            "If opponent is forcing greed on you, pivot strategy",
            "Best players adjust target range multiple times per round"
          ]
        }
      ]
    },
    "advanced_strategies": {
      "walkthrough": [
        {
          "step": 1,
          "title": "The Humble Gambit",
          "text": "One of the most powerful strategies is the deliberate Humble play. When your hand is weak, lean into it. Play your lowest cards, avoid trump, and aim for zero to three tricks. Scoring six points for Humble is just as good as scoring six for Victorious. The trick is committing early and not accidentally winning tricks you do not want.",
          "image": null,
          "image_caption": null
        },
        {
          "step": 2,
          "title": "Swan Lock Strategy",
          "text": "The Swan gives you the lead even when you lose a trick. Use this to create a \"swan lock\" where you repeatedly lead with cards that force your opponent into unfavorable positions. Lead with a suit your opponent is short on, forcing them to use trump or give you information about their hand.",
          "image": null,
          "image_caption": null
        },
        {
          "step": 3,
          "title": "Trump Timing",
          "text": "Advanced players think of trump cards as a limited resource to be deployed at the perfect moment. In the early tricks, gathering information about your opponent's hand is more valuable than winning tricks. Save your highest trumps for the last three to four tricks when you know exactly what you need. A well-timed trump can guarantee your final trick count lands in the right zone.",
          "image": null,
          "image_caption": null
        },
        {
          "step": 4,
          "title": "The Witch as a Lead Weapon",
          "text": "The Witch counts as trump when led, making it one of the most dangerous opening plays. Lead with the Witch when you need to guarantee a trick win and when your opponent likely has that suit in hand. Because they must follow suit if able, they cannot counter with trump from a different suit.",
          "image": null,
          "image_caption": null
        },
        {
          "step": 5,
          "title": "Reading Your Opponent",
          "text": "Pay close attention to what your opponent takes from the draw pile when the Woodcutter is played, and what suits they cannot follow. Every piece of information narrows down their hand. If they cannot follow Keys in trick four, every future Keys lead is guaranteed to give them a choice between trumping or discarding.",
          "image": null,
          "image_caption": null
        },
        {
          "step": 6,
          "title": "Endgame Trick Manipulation",
          "text": "In the last three or four tricks, you should know roughly what your opponent holds. Count the tricks carefully. If you are at seven and your opponent is at six, you have scored six points in the Victorious range. Your goal in the remaining tricks is to avoid winning three more. Play your lowest remaining cards and let your opponent take the final tricks.",
          "image": null,
          "image_caption": null
        },
        {
          "step": 7,
          "title": "Fox Card Timing",
          "text": "The Fox lets you swap the trump card with one from your hand. The optimal time to use this is when the current trump card is high and useful for your strategy. Swap out a card you do not need and gain a strong trump. Early Fox plays give you more tricks to benefit from the improved hand.",
          "image": null,
          "image_caption": null
        },
        {
          "step": 8,
          "title": "Multi-Round Scoring Strategy",
          "text": "Remember the game is played to 21 points across multiple rounds. If you are at 15 points and your opponent is at 8, you only need six more points. A single Victorious or Humble round wins the game. Play conservatively and aim for a guaranteed scoring zone rather than risking a Greedy zero.",
          "image": null,
          "image_caption": null
        }
      ],
      "summary": [
        {
          "step": 1,
          "title": "The Humble Gambit",
          "bullets": [
            "Deliberately aim for 0-3 tricks with a weak hand",
            "Humble = 6 pts, same as Victorious",
            "Commit early, avoid accidental trick wins"
          ]
        },
        {
          "step": 2,
          "title": "Swan Lock Strategy",
          "bullets": [
            "Swan lets you lead after losing a trick",
            "Repeatedly lead suits your opponent is short on",
            "Forces opponent into unfavorable plays"
          ]
        },
        {
          "step": 3,
          "title": "Trump Timing",
          "bullets": [
            "Treat trump as a limited resource",
            "Gather info in early tricks, deploy trump in last 3-4",
            "Well-timed trump guarantees target trick count"
          ]
        },
        {
          "step": 4,
          "title": "The Witch as a Lead Weapon",
          "bullets": [
            "Witch (9) = trump when led, guarantees the trick",
            "Opponent must follow suit, can't counter with other trump",
            "Best when opponent likely has that suit"
          ]
        },
        {
          "step": 5,
          "title": "Reading Your Opponent",
          "bullets": [
            "Track which suits opponent can't follow",
            "Each void reveals future lead opportunities",
            "Information is power in trick-taking"
          ]
        },
        {
          "step": 6,
          "title": "Endgame Trick Manipulation",
          "bullets": [
            "Last 3-4 tricks: count carefully to land in target zone",
            "If at 7 tricks, avoid winning 3 more (greedy)",
            "Play lowest remaining cards to shed tricks"
          ]
        },
        {
          "step": 7,
          "title": "Fox Card Timing",
          "bullets": [
            "Fox (3) swaps trump card with a hand card",
            "Best when trump card is high and useful",
            "Early swaps give more tricks to benefit"
          ]
        },
        {
          "step": 8,
          "title": "Multi-Round Scoring Strategy",
          "bullets": [
            "Game plays to 21 points across multiple rounds",
            "If close to winning, play conservatively",
            "Guarantee a scoring zone rather than risk Greedy 0"
          ]
        }
      ]
    },
    "appendix": {
      "entries": [
        {
          "term": "Trick",
          "definition": "A single exchange where both players play one card. The leader plays first, the follower plays second. The winner collects both cards and leads the next trick.",
          "category": "Core Concepts"
        },
        {
          "term": "Lead",
          "definition": "Playing the first card of a trick. The leader chooses any card from their hand, setting the suit that the follower must match if able.",
          "category": "Core Concepts"
        },
        {
          "term": "Follow Suit",
          "definition": "Playing a card of the same suit as the led card. You must follow suit if you have a card of that suit in your hand. If you cannot follow, you may play any card.",
          "category": "Core Concepts"
        },
        {
          "term": "Trump Suit",
          "definition": "The suit determined by the face-up card at the start of the round. Trump cards beat any non-trump card. If both cards are trump, the higher number wins.",
          "category": "Core Concepts"
        },
        {
          "term": "Bells",
          "definition": "One of the three card suits in Fox in the Forest, depicted with bell icons.",
          "category": "Suits"
        },
        {
          "term": "Keys",
          "definition": "One of the three card suits in Fox in the Forest, depicted with key icons.",
          "category": "Suits"
        },
        {
          "term": "Moons",
          "definition": "One of the three card suits in Fox in the Forest, depicted with crescent moon icons.",
          "category": "Suits"
        },
        {
          "term": "Swan (1)",
          "definition": "Special ability card. If you play the Swan and lose the trick, you lead the next trick instead of the winner. Gives you control of the lead even when losing.",
          "category": "Card Abilities"
        },
        {
          "term": "Fox (3)",
          "definition": "Special ability card. When you play the Fox, you may exchange the face-up trump card with a card from your hand. Useful for improving your trump holdings.",
          "category": "Card Abilities"
        },
        {
          "term": "Woodcutter (5)",
          "definition": "Special ability card. When you play the Woodcutter, draw one card from the draw deck and then discard one card face down. Allows you to improve your hand.",
          "category": "Card Abilities"
        },
        {
          "term": "Treasure (7)",
          "definition": "Special ability card. Whoever wins the trick containing the Treasure scores one bonus point added to their round score.",
          "category": "Card Abilities"
        },
        {
          "term": "Witch (9)",
          "definition": "Special ability card. When led, the Witch counts as trump regardless of its printed suit. A powerful surprise play that forces opponents to follow the Witch's printed suit while the Witch wins as trump.",
          "category": "Card Abilities"
        },
        {
          "term": "Monarch (11)",
          "definition": "Special ability card. You must play the Monarch if it is your only card of the led suit. This is a restriction rather than a benefit.",
          "category": "Card Abilities"
        },
        {
          "term": "Humble",
          "definition": "Scoring category for winning zero to three tricks in a round. Scores six points. A deliberate strategy when your hand is weak.",
          "category": "Scoring"
        },
        {
          "term": "Victorious",
          "definition": "Scoring category for winning seven to nine tricks in a round. Scores six points. The standard target for players with strong hands.",
          "category": "Scoring"
        },
        {
          "term": "Greedy",
          "definition": "Scoring category for winning ten to thirteen tricks in a round. Scores zero points. The penalty for dominating too much. Opponents can force you into this range.",
          "category": "Scoring"
        },
        {
          "term": "Draw Deck",
          "definition": "The six remaining cards after dealing and revealing the trump card. Used by the Woodcutter ability. Not otherwise drawn from during the round.",
          "category": "Components"
        },
        {
          "term": "Score Track",
          "definition": "The track where both players mark their cumulative score across rounds. First player to 21 points wins the game.",
          "category": "Components"
        },
        {
          "term": "Trump Card",
          "definition": "The face-up card next to the draw deck that determines the trump suit for the round. Can be swapped by the Fox ability.",
          "category": "Components"
        },
        {
          "term": "Round",
          "definition": "A complete set of 13 tricks played with a fresh deal. The game consists of multiple rounds until a player reaches 21 points.",
          "category": "Game Structure"
        },
        {
          "term": "Trick Count",
          "definition": "The number of tricks a player has won so far in the round. Constantly tracking this is essential for making strategic decisions and avoiding the Greedy trap.",
          "category": "Game Structure"
        }
      ]
    }
  }
}